[
  {
    "name": "Ivuriro Isango",
    "location": "Muhanga",
    "tel": "0788691380"
  },
  {
    "name": "Umurage Medical Clinic",
    "location": "Muhanga",
    "tel": "0788404430"
  },
  {
    "name": "Ineza clinique",
    "location": "Muhanga",
    "tel": "0788663911"
  },
  {
    "name": "Muhororo Eye Clinic",
    "location": "Muhanga",
    "tel": "No phone number"
  },
  {
    "name": "Nyabikenke Health Center",
    "location": "Muhanga",
    "tel": "No phone number"
  },
  {
    "name": "Busoro Health Clinic",
    "location": "Muhanga",
    "tel": "No phone number"
  },
  {
    "name": "BWIZA CLINIC AND DIAGNOSTIC CENTER LTD",
    "location": "Muhanga",
    "tel": "0780681459"
  },
  {
    "name": "Gitega Health Centre",
    "location": "Muhanga",
    "tel": "No phone number"
  }
]
